University/Year IV/FPGA/Lab_1/sw_led.vhd
library IEEE;
use IEEE.STD_LOGIC_1164.ALL;

entity sw_led is
	Port(A : in STD_LOGIC_VECTOR (7 downto 0);
		 Y : out STD_LOGIC_VECTOR (7 downto 0));

end sw_led;

architecture Behavioral of sw_led is

begin
	Y <= A;
	
end Behavioral;

Year IV/FPGA/Lab_1/sw_led_top.vhd
library IEEE;
use IEEE.STD_LOGIC_1164.ALL;

entity sw_led_top is 

end sw_led_top;

architecture Behavioral of sw_led_top is 
	component sw_led is 
	port (
		A: in STD_LOGIC_VECTOR (7 downto 0) ; 
		   Y : out STD_LOGIC_VECTOR (7 downto 0));
	end component;

	constant period : time := 10 ns;
	
	signal A: std_logic_vector (7 downto 0) ; 
		signal Y : std_logic_vector (7 downto 0) ; 
		
begin 
   c1: sw_led
	port map(
	 A => A, 
	 Y => Y
	 );
	 process 
	 begin 
	 A <= "00110011";
	 wait for period;
	 A <= "01110011";
	 wait for period;
	 A <= "00111011";
	 wait for period;
	 A <= "01000011";
	 wait for period;
	 end process;
	 
end Behavioral;

University/Year IV/FPGA/Lab_1/sw_led_top.vcd
$date
  Fri Oct  4 14:36:58 2024
$end
$version
  GHDL v0
$end
$timescale
  1 fs
$end
$scope module standard $end
$upscope $end
$scope module std_logic_1164 $end
$upscope $end
$scope module sw_led_top $end
$var reg 8 ! a[7:0] $end
$var reg 8 " y[7:0] $end
$scope module c1 $end
$var reg 8 # a[7:0] $end
$var reg 8 $ y[7:0] $end
$upscope $end
$upscope $end
$enddefinitions $end
#0
b00110011 !
b00110011 "
b00110011 #
b00110011 $
#10000000
b01110011 !
b01110011 "
b01110011 #
b01110011 $
#20000000
b00111011 !
b00111011 "
b00111011 #
b00111011 $
#30000000
b01000011 !
b01000011 "
b01000011 #
b01000011 $
#40000000
b00110011 !
b00110011 "
b00110011 #
b00110011 $
#50000000
b01110011 !
b01110011 "
b01110011 #
b01110011 $
#60000000
b00111011 !
b00111011 "
b00111011 #
b00111011 $
#70000000
b01000011 !
b01000011 "
b01000011 #
b01000011 $
#80000000
b00110011 !
b00110011 "
b00110011 #
b00110011 $
#90000000
b01110011 !
b01110011 "
b01110011 #
b01110011 $
#100000000
b00111011 !
b00111011 "
b00111011 #
b00111011 $
